metro/__init__.py
metro-0.0.1.dist-info/LICENSE
metro-0.0.1.dist-info/METADATA
metro-0.0.1.dist-info/WHEEL
metro-0.0.1.dist-info/top_level.txt
metro-0.0.1.dist-info/RECORD
