Metadata-Version: 2.1
Name: metro
Version: 0.0.1
Summary: Metro framework for Airflow
Home-page: https://github.com/yourhiro/metro
Author: Insert Overwrite
License: Apache License 2.0
Platform: UNKNOWN
Classifier: Programming Language :: Python :: 3
Classifier: License :: OSI Approved :: Apache Software License
Classifier: Operating System :: OS Independent
Requires-Dist: apache-airflow
